AKCK_LFF/PW92.py
AKCK_LFF/PZ81.py
AKCK_LFF/QMC_data.py
AKCK_LFF/__init__.py
AKCK_LFF/alda.py
AKCK_LFF/alpha_c_c1.py
AKCK_LFF/asymptotics.py
AKCK_LFF/corr.py
AKCK_LFF/fit_LFF.py
AKCK_LFF/fit_RPA_cutoffs.py
AKCK_LFF/fitted_LFF.py
AKCK_LFF/g_corradini.py
AKCK_LFF/gauss_quad.py
AKCK_LFF/global_plot_pars.py
AKCK_LFF/mcp07_static.py
AKCK_LFF/plot_LFFs.py
AKCK_LFF/rMCP07.py
AKCK_LFF/ra_lff.py
AKCK_LFF/stiffness_refit.py
AKCK_LFF/surf_plots.py
AKCK_LFF-1.0.1.dist-info/LICENSE
AKCK_LFF-1.0.1.dist-info/METADATA
AKCK_LFF-1.0.1.dist-info/WHEEL
AKCK_LFF-1.0.1.dist-info/top_level.txt
AKCK_LFF-1.0.1.dist-info/RECORD
