Metadata-Version: 2.1
Name: AKCK-LFF
Version: 1.0.1
Summary: Analytic models for the local field factors of the interacting uniform electron gas
Author-email: Aaron Kaplan <aaron.kaplan.physics@gmail.com>, Carl Kukkonen <kukkonen@viaspace.com>
License: Creative Commons Legal Code
Project-URL: Homepage, https://github.com/esoteric-ephemera/UEG_LFF
Project-URL: Bug Tracker, https://github.com/esoteric-ephemera/UEG_LFF/issues
Classifier: Programming Language :: Python :: 3
Classifier: Operating System :: OS Independent
Requires-Python: >=3.7
License-File: LICENSE
Requires-Dist: numpy
Requires-Dist: scipy
Requires-Dist: matplotlib
